WokeyTalky/Woke_Pipeline.py
WokeyTalky/__init__.py
WokeyTalky/feedforward.py
WokeyTalky/gpt_judge.py
WokeyTalky/prompt_loss.py
WokeyTalky/utils/__init__.py
WokeyTalky/utils/claude_generation.py
WokeyTalky/utils/config_util.py
WokeyTalky/utils/eval_util.py
WokeyTalky/utils/gemini_generation.py
WokeyTalky/utils/gpt_batch_request.py
WokeyTalky/utils/gpt_generation.py
WokeyTalky/utils/progress_util.py
WokeyTalky/utils/prompt_util.py
WokeyTalky/utils/util.py
WokeyTalky-0.1.3.dist-info/LICENSE
WokeyTalky-0.1.3.dist-info/METADATA
WokeyTalky-0.1.3.dist-info/WHEEL
WokeyTalky-0.1.3.dist-info/top_level.txt
WokeyTalky-0.1.3.dist-info/RECORD
