Metadata-Version: 2.1
Name: WokeyTalky
Version: 0.1.3
Summary: A scalable and dynamic pipeline set for generation of spurious features.
Author-email: Adam Nguyen <Adanato@vt.edu>
Project-URL: Homepage, https://github.com/ruoxi-jia-group/Woke-Pipeline
Project-URL: Issues, https://github.com/ruoxi-jia-group/Woke-Pipeline/issues
Classifier: Programming Language :: Python :: 3
Classifier: License :: OSI Approved :: MIT License
Classifier: Operating System :: OS Independent
Requires-Python: >=3.9
License-File: LICENSE
